gpdvega/__init__.py
gpdvega/geodata.py
gpdvega-0.1.1rc1.dist-info/METADATA
gpdvega-0.1.1rc1.dist-info/RECORD
gpdvega-0.1.1rc1.dist-info/WHEEL
gpdvega-0.1.1rc1.dist-info/top_level.txt
