Metadata-Version: 2.1
Name: gpdvega
Version: 0.1.1rc1
Summary: GpdVega GeoPandas and Altair intergation
Home-page: https://iliatimofeev.github.io/gpdvega/
Author: Ilia Timofeev
Author-email: ilia.timofeev@gmail.com
License: BSD 3-clause
Download-URL: https://github.com/iliatimofeev/gpdvega
Platform: UNKNOWN
Classifier: Development Status :: 3 - Alpha
Classifier: Environment :: Console
Classifier: Intended Audience :: Science/Research
Classifier: License :: OSI Approved :: BSD License
Classifier: Natural Language :: English
Classifier: Programming Language :: Python :: 2.7
Classifier: Programming Language :: Python :: 3.4
Classifier: Programming Language :: Python :: 3.5
Classifier: Programming Language :: Python :: 3.6
Provides-Extra: dev
